processamento_imagens_pythonico/__init__.py
processamento_imagens_pythonico/processing/__init__.py
processamento_imagens_pythonico/processing/combination.py
processamento_imagens_pythonico/processing/transformation.py
processamento_imagens_pythonico/utils/__init__.py
processamento_imagens_pythonico/utils/io.py
processamento_imagens_pythonico/utils/plot.py
processamento_imagens_pythonico-0.0.1.dist-info/METADATA
processamento_imagens_pythonico-0.0.1.dist-info/WHEEL
processamento_imagens_pythonico-0.0.1.dist-info/top_level.txt
processamento_imagens_pythonico-0.0.1.dist-info/RECORD
